<?xml version="1.0" encoding="utf-8"?>
<data>
	<List>
		<FBID>1553042695</FBID>
		<Name>Wei Chang</Name>
		<Text>環境整潔，也設置許多給小孩玩的設施，而且老闆態度親切且貼心。</Text>
		<DateTime>2012-10-02 16:48</DateTime>
	</List>
	<List>
		<FBID>1553042695</FBID>
		<Name>Wei Chang</Name>
		<Text>請問這裡要是事先訂位嗎？</Text>
		<DateTime>2012-10-02 16:49</DateTime>
	</List>
	<List>
		<FBID>1553042695</FBID>
		<Name>Wei Chang</Name>
		<Text>這個餐廳真的很不錯! 餐點新鮮份量足，量真的很多那種喔! 胃口大的看了會很開心 !呵呵~~ 吃飽飽到周邊走走好消化。</Text>
		<DateTime>2012-10-02 16:48</DateTime>
	</List>
	<List>
		<FBID>1553042695</FBID>
		<Name>Wei Chang</Name>
		<Text>感謝每一位前來的父母，你們的建議我們會盡全力去改進、謝謝你們的支持。</Text>
		<DateTime>2012-10-02 16:48</DateTime>
	</List>
	<List>
		<FBID>1553042695</FBID>
		<Name>Wei Chang</Name>
		<Text>今天帶小孩去玩，玩到都不想回家@@沒有入園費，也沒低消，但車位與另家咖啡廳共用，需要找一下停車位。</Text>
		<DateTime>2012-10-02 16:48</DateTime>
	</List>
	<List>
		<FBID>1553042695</FBID>
		<Name>Wei Chang</Name>
		<Text>環境整潔，也設置許多給小孩玩的設施，而且老闆態度親切且貼心。</Text>
		<DateTime>2012-10-02 16:48</DateTime>
	</List>
	<List>
		<FBID>1553042695</FBID>
		<Name>Wei Chang</Name>
		<Text>請問這裡要是事先訂位嗎？</Text>
		<DateTime>2012-10-02 16:48</DateTime>
	</List>
	<List>
		<FBID>1553042695</FBID>
		<Name>Wei Chang</Name>
		<Text>這個餐廳真的很不錯! 餐點新鮮份量足，量真的很多那種喔! 胃口大的看了會很開心 !呵呵~~ 吃飽飽到周邊走走好消化。</Text>
		<DateTime>2012-10-02 16:48</DateTime>
	</List>
	<List>
		<FBID>1553042695</FBID>
		<Name>Wei Chang</Name>
		<Text>感謝每一位前來的父母，你們的建議我們會盡全力去改進、謝謝你們的支持。</Text>
		<DateTime>2012-10-02 16:48</DateTime>
	</List>
</data>